cloudbaseinit/__init__.py
cloudbaseinit/constant.py
cloudbaseinit/exception.py
cloudbaseinit/init.py
cloudbaseinit/shell.py
cloudbaseinit/version.py
cloudbaseinit/conf/__init__.py
cloudbaseinit/conf/azure.py
cloudbaseinit/conf/base.py
cloudbaseinit/conf/cloudconfig.py
cloudbaseinit/conf/cloudstack.py
cloudbaseinit/conf/default.py
cloudbaseinit/conf/ec2.py
cloudbaseinit/conf/factory.py
cloudbaseinit/conf/gce.py
cloudbaseinit/conf/maas.py
cloudbaseinit/conf/nocloud.py
cloudbaseinit/conf/openstack.py
cloudbaseinit/conf/opts.py
cloudbaseinit/conf/ovf.py
cloudbaseinit/conf/packet.py
cloudbaseinit/conf/vmwareguestinfo.py
cloudbaseinit/metadata/__init__.py
cloudbaseinit/metadata/factory.py
cloudbaseinit/metadata/services/__init__.py
cloudbaseinit/metadata/services/azureservice.py
cloudbaseinit/metadata/services/base.py
cloudbaseinit/metadata/services/baseconfigdrive.py
cloudbaseinit/metadata/services/baseopenstackservice.py
cloudbaseinit/metadata/services/cloudstack.py
cloudbaseinit/metadata/services/configdrive.py
cloudbaseinit/metadata/services/ec2service.py
cloudbaseinit/metadata/services/gceservice.py
cloudbaseinit/metadata/services/httpservice.py
cloudbaseinit/metadata/services/maasservice.py
cloudbaseinit/metadata/services/nocloudservice.py
cloudbaseinit/metadata/services/opennebulaservice.py
cloudbaseinit/metadata/services/ovfservice.py
cloudbaseinit/metadata/services/packet.py
cloudbaseinit/metadata/services/vmwareguestinfoservice.py
cloudbaseinit/metadata/services/osconfigdrive/__init__.py
cloudbaseinit/metadata/services/osconfigdrive/base.py
cloudbaseinit/metadata/services/osconfigdrive/factory.py
cloudbaseinit/metadata/services/osconfigdrive/windows.py
cloudbaseinit/models/__init__.py
cloudbaseinit/models/network.py
cloudbaseinit/osutils/__init__.py
cloudbaseinit/osutils/base.py
cloudbaseinit/osutils/factory.py
cloudbaseinit/osutils/posix.py
cloudbaseinit/osutils/windows.py
cloudbaseinit/plugins/__init__.py
cloudbaseinit/plugins/factory.py
cloudbase_init-1.1.6.dist-info/AUTHORS
cloudbase_init-1.1.6.dist-info/LICENSE
cloudbase_init-1.1.6.dist-info/METADATA
cloudbase_init-1.1.6.dist-info/WHEEL
cloudbase_init-1.1.6.dist-info/entry_points.txt
cloudbase_init-1.1.6.dist-info/pbr.json
cloudbase_init-1.1.6.dist-info/top_level.txt
cloudbase_init-1.1.6.dist-info/RECORD
