Metadata-Version: 2.1
Name: cloudbase-init
Version: 1.1.6
Summary: Portable cloud initialization service
Home-page: http://www.cloudbase.it/
Author: Cloudbase Solutions Srl
Author-email: apilotti@cloudbasesolutions.com
License: UNKNOWN
Platform: UNKNOWN
Classifier: Environment :: OpenStack
Classifier: Intended Audience :: Information Technology
Classifier: Intended Audience :: System Administrators
Classifier: License :: OSI Approved :: Apache Software License
Classifier: Operating System :: OS Independent
Classifier: Programming Language :: Python
Classifier: Programming Language :: Python :: 3
Classifier: Programming Language :: Python :: 3.8
Classifier: Programming Language :: Python :: 3.9
Classifier: Programming Language :: Python :: 3.10
Classifier: Programming Language :: Python :: 3.11
Classifier: Programming Language :: Python :: 3.12
Requires-Dist: Babel (>=1.3)
Requires-Dist: PyYAML
Requires-Dist: cryptography
Requires-Dist: iso8601
Requires-Dist: jinja2
Requires-Dist: netaddr (>=0.7.6)
Requires-Dist: netifaces
Requires-Dist: oauthlib
Requires-Dist: oslo.config
Requires-Dist: oslo.log
Requires-Dist: pbr (>=2.0.0)
Requires-Dist: pyserial
Requires-Dist: requests
Requires-Dist: untangle (==1.2.1)
Requires-Dist: comtypes ; (sys_platform=="win32")
Requires-Dist: pymi ; (sys_platform=="win32")
Requires-Dist: pywin32 ; (sys_platform=="win32")
Requires-Dist: tzlocal ; (sys_platform=="win32")
Requires-Dist: wmi ; (sys_platform=="win32")
